netbox_ping/__init__.py
netbox_ping/apps.py
netbox_ping/config.py
netbox_ping/forms.py
netbox_ping/hooks.py
netbox_ping/models.py
netbox_ping/navigation.py
netbox_ping/plugin.py
netbox_ping/signals.py
netbox_ping/tables.py
netbox_ping/template_content.py
netbox_ping/template_extensions.py
netbox_ping/urls.py
netbox_ping/utils.py
netbox_ping/views.py
netbox_ping/api/__init__.py
netbox_ping/api/serializers.py
netbox_ping/api/urls.py
netbox_ping/api/views.py
netbox_ping/migrations/0001_initial.py
netbox_ping/migrations/0002_add_dns_fields.py
netbox_ping/migrations/0003_add_dns_name_field.py
netbox_ping/migrations/__init__.py
netbox_ping/migrations/__pycache__/0001_initial.cpython-312.pyc
netbox_ping/migrations/__pycache__/0002_add_dns_fields.cpython-312.pyc
netbox_ping/migrations/__pycache__/0003_add_dns_name_field.cpython-312.pyc
netbox_ping/migrations/__pycache__/__init__.cpython-312.pyc
netbox_ping/templates/netbox_ping/compare_interfaces_button.html
netbox_ping/templates/netbox_ping/interface_comparison.html
netbox_ping/templates/netbox_ping/number_of_interfaces_panel.html
netbox_ping/templates/netbox_ping/ping_home.html
netbox_ping/templates/netbox_ping/ping_subnet_button.html
netbox_ping/templates/netbox_ping/prefix_button.html
netbox_ping/templates/netbox_ping/prefix_content.html
netbox_ping-0.54.dist-info/METADATA
netbox_ping-0.54.dist-info/WHEEL
netbox_ping-0.54.dist-info/top_level.txt
netbox_ping-0.54.dist-info/RECORD
