Metadata-Version: 2.2
Name: netbox-ping
Version: 0.54
Summary: A NetBox plugin for pinging and discovering IPs
Home-page: https://github.com/dendanskemine/netbox-ping
Author: Christian Rose
License: Apache 2.0
Classifier: Development Status :: 4 - Beta
Classifier: Framework :: Django
Classifier: Programming Language :: Python :: 3
Classifier: Programming Language :: Python :: 3.8
Classifier: Programming Language :: Python :: 3.9
Classifier: Programming Language :: Python :: 3.12
Requires-Dist: dnspython>=2.0.0
Dynamic: author
Dynamic: classifier
Dynamic: description
Dynamic: description-content-type
Dynamic: home-page
Dynamic: license
Dynamic: requires-dist
Dynamic: summary
